streamlit_authenticator_mongo/__init__.py
streamlit_authenticator_mongo/authenticate.py
streamlit_authenticator_mongo/db.py
streamlit_authenticator_mongo/exceptions.py
streamlit_authenticator_mongo/hasher.py
streamlit_authenticator_mongo/utils.py
streamlit_authenticator_mongo/validator.py
streamlit_authenticator_mongo-0.1.5.dist-info/LICENSE
streamlit_authenticator_mongo-0.1.5.dist-info/METADATA
streamlit_authenticator_mongo-0.1.5.dist-info/WHEEL
streamlit_authenticator_mongo-0.1.5.dist-info/top_level.txt
streamlit_authenticator_mongo-0.1.5.dist-info/RECORD
