Metadata-Version: 2.1
Name: streamlit-authenticator-mongo
Version: 0.1.5
Summary: A secure authentication module to validate user credentials and insert user credentails in Mongodb with streamlit.
Home-page: https://github.com/RobotForge/Streamlit-Authenticator-mongo
Author: Kegbokokim Ibok
Author-email: ibokkegbo@robotforge.co
Keywords: Python,Streamlit,Authentication,Components,MongoDB
Classifier: Programming Language :: Python :: 3
Classifier: License :: OSI Approved :: MIT License
Classifier: Operating System :: OS Independent
Requires-Python: >=3.6
License-File: LICENSE
Requires-Dist: PyJWT >=2.3.0
Requires-Dist: bcrypt >=3.1.7
Requires-Dist: PyYAML >=5.3.1
Requires-Dist: streamlit >=1.18.0
Requires-Dist: extra-streamlit-components >=0.1.60
Requires-Dist: pymongo >=4.6.0
